tiavda/VERSION
tiavda/__init__.py
tiavda/version.py
tiavda/color/__init__.py
tiavda/color/color_palette.py
tiavda/plotting/__init__.py
tiavda/plotting/adata_plots_two_dimensional.py
tiavda/plotting/density_plots.py
tiavda-0.5.dist-info/LICENSE
tiavda-0.5.dist-info/METADATA
tiavda-0.5.dist-info/WHEEL
tiavda-0.5.dist-info/entry_points.txt
tiavda-0.5.dist-info/top_level.txt
tiavda-0.5.dist-info/RECORD
