Metadata-Version: 2.1
Name: tiavda
Version: 0.5
Summary: tiavda graphing util package
Home-page: https://github.com/AdvaitPavuluri/tiavda
Author: Advait Pavuluri
Author-email: advait.pavuluri@gmail.com
License: UNKNOWN
Platform: UNKNOWN
Classifier: Programming Language :: Python :: 3
Classifier: License :: OSI Approved :: GNU General Public License v3 (GPLv3)
Classifier: Operating System :: OS Independent
Requires-Python: >=3.6
Requires-Dist: cryptography (>=3.4.4)
Requires-Dist: fabric (>=2.6.0)
Requires-Dist: paramiko (>=2.7.2)
Requires-Dist: requests (>=2.25.1)
Requires-Dist: apache-libcloud (>=3.3.1)
